setup.py
little_module_loader/__init__.py
little_module_loader.egg-info/PKG-INFO
little_module_loader.egg-info/SOURCES.txt
little_module_loader.egg-info/dependency_links.txt
little_module_loader.egg-info/top_level.txt