Metadata-Version: 1.0
Name: little-module-loader
Version: 0.2
Summary: A very simple module loader package for dynamically creating lists of modules, classes, and functions
Home-page: http://russellhay.com/tagged/little
Author: Russell Hay
Author-email: me@russellhay.com
License: PSF
Platform: UNKNOWN
